{"assets":{"500251E8DEC407F09E1DCC95A9A04274":{"type":"texture","index":6,"assetRequest":{"type":"slide","state":"contents","slide":"none"},"url":{"native":"assets\/3FE37D04-764A-4489-AAF8-01DE799FB0C2.pdf"},"width":720,"height":405},"ACA29B21A7C35BBFE2D04B0DFB1F9D0F":{"type":"texture","index":4,"assetRequest":{"type":"slide","state":"contents","slide":"none"},"url":{"native":"assets\/3FE37D04-764A-4489-AAF8-01DE799FB0C2.pdf"},"width":718,"height":397},"F7A29D79CCDDC21925033B223E2700F5":{"type":"texture","index":5,"assetRequest":{"type":"slide","state":"contents","slide":"none"},"url":{"native":"assets\/3FE37D04-764A-4489-AAF8-01DE799FB0C2.pdf"},"width":17,"height":12},"0DF7A63E368CD5F4EF722AAF54AE841C":{"type":"texture","index":1,"assetRequest":{"type":"slide","state":"contents","slide":"none"},"url":{"native":"assets\/3FE37D04-764A-4489-AAF8-01DE799FB0C2.pdf"},"width":411,"height":293},"C2B660CBAE4E04024987B6A2AAA101E6":{"type":"texture","index":2,"assetRequest":{"type":"slide","state":"contents","slide":"none"},"url":{"native":"assets\/3FE37D04-764A-4489-AAF8-01DE799FB0C2.pdf"},"width":617,"height":31},"DA4973FF21027C87B166D858FEECF4FC":{"type":"texture","index":3,"assetRequest":{"type":"slide","state":"contents","slide":"none"},"url":{"native":"assets\/3FE37D04-764A-4489-AAF8-01DE799FB0C2.pdf"},"width":324,"height":197},"1BFD4A8A3262821D77512FEA63730126":{"type":"texture","index":0,"assetRequest":{"type":"slide","state":"contents","slide":"none"},"url":{"native":"assets\/3FE37D04-764A-4489-AAF8-01DE799FB0C2.pdf"},"width":720,"height":405},"414597C22F1B90C06D244B46B4458540":{"type":"texture","index":7,"assetRequest":{"type":"slide","state":"contents","slide":"none"},"url":{"native":"assets\/3FE37D04-764A-4489-AAF8-01DE799FB0C2.pdf"},"width":720,"height":405}},"events":[{"effects":[{"beginTime":0,"baseLayer":{"animations":[],"initialState":{"affineTransform":[1,0,0,1,0,0],"masksToBounds":false,"rotation":0,"scale":1,"position":{"pointX":505.11660766601562,"pointY":208.50031661987305},"width":411,"sublayerTransform":[1,0,0,0,0,1,0,0,0,0,1,0,0,0,0,1],"contentsRect":{"y":0,"x":0,"width":1,"height":1},"opacity":1,"edgeAntialiasingMask":251658240,"height":293,"hidden":false,"anchorPoint":{"pointX":0.5,"pointY":0.5}},"objectID":"B8E87B26-F9FB-4880-8E13-91E059967AC1","layers":[{"animations":[],"initialState":{"affineTransform":[1,0,0,1,0,0],"masksToBounds":false,"rotation":0,"scale":1,"position":{"pointX":60.383392333984375,"pointY":140.49968338012695},"width":411,"sublayerTransform":[1,0,0,0,0,1,0,0,0,0,1,-0.00093354433244735948,0,0,0,1],"contentsRect":{"y":0,"x":0,"width":1,"height":1},"opacity":1,"edgeAntialiasingMask":251658240,"height":293,"hidden":false,"anchorPoint":{"pointX":0.14691822952307634,"pointY":0.47952110368644013}},"layers":[{"animations":[{"additive":false,"timeOffset":0,"beginTime":1e-100,"repeatCount":0,"fillMode":"both","duration":0.01,"autoreverses":false,"animations":[{"additive":false,"timeOffset":0,"beginTime":0,"from":{"scalar":true},"repeatCount":0,"fillMode":"both","duration":0.0001,"autoreverses":false,"property":"hidden","to":{"scalar":false},"removedOnCompletion":true},{"additive":false,"timeOffset":0,"beginTime":0.0001,"from":{"scalar":false},"repeatCount":0,"fillMode":"forwards","duration":0.0099000000000000008,"autoreverses":false,"property":"hidden","to":{"scalar":false},"removedOnCompletion":true}],"removedOnCompletion":false}],"layers":[],"texturedRectangle":{"isBackgroundTexture":true,"singleTextureOpacity":1,"textureType":5,"textBaseline":0,"textXHeight":0,"isVerticalText":false},"initialState":{"affineTransform":[1,0,0,1,0,0],"masksToBounds":false,"rotation":0,"scale":1,"position":{"pointX":203.88339233398438,"pointY":145.49968338012695},"width":411,"sublayerTransform":[1,0,0,0,0,1,0,0,0,0,1,0,0,0,0,1],"contentsRect":{"y":0,"x":0,"width":1,"height":1},"opacity":1,"edgeAntialiasingMask":0,"height":293,"hidden":true,"anchorPoint":{"pointX":0.5,"pointY":0.5}},"texture":"0DF7A63E368CD5F4EF722AAF54AE841C"}]}]},"effects":[],"duration":0.01,"type":"buildIn","attributes":{"direction":0},"name":"apple:appear","objectID":"B8E87B26-F9FB-4880-8E13-91E059967AC1"}],"automaticPlay":false,"hyperlinks":[],"accessibility":[{"text":"These seemingly tiny Web communities can really punch above their weight class when it comes to influencing the greater Web","targetRectangle":{"y":149.14644777151989,"x":128.42054882049561,"width":404.64999999999998,"height":123.37515258789062}},{"text":"Twitter top influencers for alternative URLs ","targetRectangle":{"y":88.807092189788818,"x":34.098265171051025,"width":316.31899999999996,"height":22.942489133474737}},{"text":"\/r\/The_Donald (2.72%)","targetRectangle":{"y":111.74958132326356,"x":90.347399592399597,"width":147.73500000000001,"height":20.030619838535131}},{"text":"\/pol\/ (1.96%)","targetRectangle":{"y":131.78020116179869,"x":90.347399592399597,"width":84.225000000000023,"height":20.030619838535131}},{"text":"\/r\/politics (1.1%)","targetRectangle":{"y":151.81082100033382,"x":90.347399592399597,"width":106.72500000000002,"height":20.030619838535131}},{"text":"Twitter top influencers for mainstream URLs","targetRectangle":{"y":200.78392997234369,"x":34.098265171051025,"width":320.58599999999996,"height":27.942489133474737}},{"text":"\/r\/politics (4.29%)","targetRectangle":{"y":228.72641910581842,"x":90.347399592399597,"width":115.065,"height":20.030619838535131}},{"text":"\/pol\/ (3.01%)","targetRectangle":{"y":248.75703894435355,"x":90.347399592399597,"width":84.225000000000023,"height":20.030619838535131}},{"text":"\/r\/The_Donald (2.97%)","targetRectangle":{"y":268.78765878288868,"x":90.347399592399597,"width":147.73500000000001,"height":17.625091552734375}},{"text":"￼","targetRectangle":{"y":379.30624362136621,"x":667.05599963665009,"width":13.344000000000051,"height":13.7000732421875}},{"text":"How Communities Influence Each Other?","targetRectangle":{"y":11.819133758544922,"x":24.80990743637085,"width":618.05200000000002,"height":40.15020751953125}}],"baseLayer":{"animations":[],"initialState":{"affineTransform":[1,0,0,1,0,0],"masksToBounds":false,"rotation":0,"scale":1,"position":{"pointX":360,"pointY":202.5},"width":720,"sublayerTransform":[1,0,0,0,0,1,0,0,0,0,1,0,0,0,0,1],"contentsRect":{"y":0,"x":0,"width":1,"height":1},"opacity":1,"edgeAntialiasingMask":251658240,"height":405,"hidden":false,"anchorPoint":{"pointX":0.5,"pointY":0.5}},"layers":[{"animations":[],"initialState":{"affineTransform":[1,0,0,1,0,0],"masksToBounds":false,"rotation":0,"scale":1,"position":{"pointX":360,"pointY":202.5},"width":720,"sublayerTransform":[1,0,0,0,0,1,0,0,0,0,1,0,0,0,0,1],"contentsRect":{"y":0,"x":0,"width":1,"height":1},"opacity":1,"edgeAntialiasingMask":251658240,"height":405,"hidden":false,"anchorPoint":{"pointX":0.5,"pointY":0.5}},"layers":[{"animations":[],"initialState":{"affineTransform":[1,0,0,1,0,0],"masksToBounds":false,"rotation":0,"scale":1,"position":{"pointX":360,"pointY":202.5},"width":720,"sublayerTransform":[1,0,0,0,0,1,0,0,0,0,1,0,0,0,0,1],"contentsRect":{"y":0,"x":0,"width":1,"height":1},"opacity":1,"edgeAntialiasingMask":251658240,"height":405,"hidden":false,"anchorPoint":{"pointX":0.5,"pointY":0.5}},"layers":[{"animations":[],"layers":[],"texturedRectangle":{"isBackgroundTexture":true,"singleTextureOpacity":1,"textureType":1,"textBaseline":0,"textXHeight":0,"isVerticalText":false},"initialState":{"affineTransform":[1,0,0,1,0,0],"masksToBounds":false,"rotation":0,"scale":1,"position":{"pointX":360,"pointY":202.5},"width":720,"sublayerTransform":[1,0,0,0,0,1,0,0,0,0,1,0,0,0,0,1],"contentsRect":{"y":0,"x":0,"width":1,"height":1},"opacity":1,"edgeAntialiasingMask":0,"height":405,"hidden":false,"anchorPoint":{"pointX":0.5,"pointY":0.5}},"texture":"1BFD4A8A3262821D77512FEA63730126"}]}]},{"animations":[],"initialState":{"affineTransform":[1,0,0,1,0,0],"masksToBounds":false,"rotation":0,"scale":1,"position":{"pointX":360,"pointY":202.5},"width":720,"sublayerTransform":[1,0,0,0,0,1,0,0,0,0,1,0,0,0,0,1],"contentsRect":{"y":0,"x":0,"width":1,"height":1},"opacity":1,"edgeAntialiasingMask":251658240,"height":405,"hidden":false,"anchorPoint":{"pointX":0.5,"pointY":0.5}},"layers":[{"animations":[],"initialState":{"affineTransform":[1,0,0,1,0,0],"masksToBounds":false,"rotation":0,"scale":1,"position":{"pointX":505.11660766601562,"pointY":208.50031661987305},"width":411,"sublayerTransform":[1,0,0,0,0,1,0,0,0,0,1,0,0,0,0,1],"contentsRect":{"y":0,"x":0,"width":1,"height":1},"opacity":1,"edgeAntialiasingMask":251658240,"height":293,"hidden":false,"anchorPoint":{"pointX":0.5,"pointY":0.5}},"objectID":"B8E87B26-F9FB-4880-8E13-91E059967AC1","layers":[{"animations":[],"layers":[],"texturedRectangle":{"isBackgroundTexture":true,"singleTextureOpacity":1,"textureType":5,"textBaseline":0,"textXHeight":0,"isVerticalText":false},"initialState":{"affineTransform":[1,0,0,1,0,0],"masksToBounds":false,"rotation":0,"scale":1,"position":{"pointX":203.88339233398438,"pointY":145.49968338012695},"width":411,"sublayerTransform":[1,0,0,0,0,1,0,0,0,0,1,0,0,0,0,1],"contentsRect":{"y":0,"x":0,"width":1,"height":1},"opacity":1,"edgeAntialiasingMask":0,"height":293,"hidden":true,"anchorPoint":{"pointX":0.5,"pointY":0.5}},"texture":"0DF7A63E368CD5F4EF722AAF54AE841C"}]}]},{"animations":[],"initialState":{"affineTransform":[1,0,0,1,0,0],"masksToBounds":false,"rotation":0,"scale":1,"position":{"pointX":360,"pointY":202.5},"width":720,"sublayerTransform":[1,0,0,0,0,1,0,0,0,0,1,0,0,0,0,1],"contentsRect":{"y":0,"x":0,"width":1,"height":1},"opacity":1,"edgeAntialiasingMask":251658240,"height":405,"hidden":false,"anchorPoint":{"pointX":0.5,"pointY":0.5}},"layers":[{"animations":[],"initialState":{"affineTransform":[1,0,0,1,0,0],"masksToBounds":false,"rotation":0,"scale":1,"position":{"pointX":329.70990753173828,"pointY":17.719133853912354},"width":617,"sublayerTransform":[1,0,0,0,0,1,0,0,0,0,1,0,0,0,0,1],"contentsRect":{"y":0,"x":0,"width":1,"height":1},"opacity":1,"edgeAntialiasingMask":251658240,"height":31,"hidden":false,"anchorPoint":{"pointX":0.5,"pointY":0.5}},"layers":[{"animations":[],"layers":[],"texturedRectangle":{"singleTextureOpacity":1,"textXHeight":0.53193548387096778,"textBaseline":0.89861802131898938,"isBackgroundTexture":true,"isVerticalText":false,"textColor":[0.58435440063476562,0.21667070686817169,0.20682203769683838,1],"textureType":6},"initialState":{"affineTransform":[1,0,0,1,0,0],"masksToBounds":false,"rotation":0,"scale":1,"position":{"pointX":313.29009246826172,"pointY":28.280866146087646},"width":617,"sublayerTransform":[1,0,0,0,0,1,0,0,0,0,1,0,0,0,0,1],"contentsRect":{"y":0,"x":0,"width":1,"height":1},"opacity":1,"edgeAntialiasingMask":0,"height":31,"hidden":false,"anchorPoint":{"pointX":0.5,"pointY":0.5}},"texture":"C2B660CBAE4E04024987B6A2AAA101E6"}]}]},{"animations":[],"initialState":{"affineTransform":[1,0,0,1,0,0],"masksToBounds":false,"rotation":0,"scale":1,"position":{"pointX":360,"pointY":202.5},"width":720,"sublayerTransform":[1,0,0,0,0,1,0,0,0,0,1,0,0,0,0,1],"contentsRect":{"y":0,"x":0,"width":1,"height":1},"opacity":1,"edgeAntialiasingMask":251658240,"height":405,"hidden":false,"anchorPoint":{"pointX":0.5,"pointY":0.5}},"layers":[{"animations":[],"initialState":{"affineTransform":[1,0,0,1,0,0],"masksToBounds":false,"rotation":0,"scale":1,"position":{"pointX":174.49865818023682,"pointY":183.70709228515625},"width":324,"sublayerTransform":[1,0,0,0,0,1,0,0,0,0,1,0,0,0,0,1],"contentsRect":{"y":0,"x":0,"width":1,"height":1},"opacity":1,"edgeAntialiasingMask":251658240,"height":197,"hidden":false,"anchorPoint":{"pointX":0.5,"pointY":0.5}},"layers":[{"animations":[],"layers":[],"texturedRectangle":{"singleTextureOpacity":1,"textXHeight":0.041248730964467011,"textBaseline":1.0630623837956952,"isBackgroundTexture":true,"isVerticalText":false,"textColor":[0,0,0,1],"textureType":6},"initialState":{"affineTransform":[1,0,0,1,0,0],"masksToBounds":false,"rotation":0,"scale":1,"position":{"pointX":181.50134181976318,"pointY":103.29290771484375},"width":324,"sublayerTransform":[1,0,0,0,0,1,0,0,0,0,1,0,0,0,0,1],"contentsRect":{"y":0,"x":0,"width":1,"height":1},"opacity":1,"edgeAntialiasingMask":0,"height":197,"hidden":false,"anchorPoint":{"pointX":0.5,"pointY":0.5}},"texture":"DA4973FF21027C87B166D858FEECF4FC"}]}]},{"animations":[],"initialState":{"affineTransform":[1,0,0,1,0,0],"masksToBounds":false,"rotation":0,"scale":1,"position":{"pointX":360,"pointY":202.5},"width":720,"sublayerTransform":[1,0,0,0,0,1,0,0,0,0,1,0,0,0,0,1],"contentsRect":{"y":0,"x":0,"width":1,"height":1},"opacity":1,"edgeAntialiasingMask":251658240,"height":405,"hidden":false,"anchorPoint":{"pointX":0.5,"pointY":0.5}},"layers":[{"animations":[],"initialState":{"affineTransform":[1,0,0,1,0,0],"masksToBounds":false,"rotation":0,"scale":1,"position":{"pointX":365.40677165985107,"pointY":204.87212610244751},"width":718,"sublayerTransform":[1,0,0,0,0,1,0,0,0,0,1,0,0,0,0,1],"contentsRect":{"y":0,"x":0,"width":1,"height":1},"opacity":1,"edgeAntialiasingMask":251658240,"height":397,"hidden":false,"anchorPoint":{"pointX":0.5,"pointY":0.5}},"objectID":"7C477E16-AD9D-4CC7-B052-550D6A50C152","layers":[{"animations":[],"layers":[],"texturedRectangle":{"isBackgroundTexture":true,"singleTextureOpacity":1,"textureType":5,"textBaseline":0,"textXHeight":0,"isVerticalText":false},"initialState":{"affineTransform":[1,0,0,1,0,0],"masksToBounds":false,"rotation":0,"scale":1,"position":{"pointX":356.59322834014893,"pointY":196.12787389755249},"width":718,"sublayerTransform":[1,0,0,0,0,1,0,0,0,0,1,0,0,0,0,1],"contentsRect":{"y":0,"x":0,"width":1,"height":1},"opacity":1,"edgeAntialiasingMask":0,"height":397,"hidden":true,"anchorPoint":{"pointX":0.5,"pointY":0.5}},"texture":"ACA29B21A7C35BBFE2D04B0DFB1F9D0F"}]}]},{"animations":[],"initialState":{"affineTransform":[1,0,0,1,0,0],"masksToBounds":false,"rotation":0,"scale":1,"position":{"pointX":360,"pointY":202.5},"width":720,"sublayerTransform":[1,0,0,0,0,1,0,0,0,0,1,0,0,0,0,1],"contentsRect":{"y":0,"x":0,"width":1,"height":1},"opacity":1,"edgeAntialiasingMask":251658240,"height":405,"hidden":false,"anchorPoint":{"pointX":0.5,"pointY":0.5}},"layers":[{"animations":[],"initialState":{"affineTransform":[1,0,0,1,0,0],"masksToBounds":false,"rotation":0,"scale":1,"position":{"pointX":670.95599973201752,"pointY":381.70624371673364},"width":17,"sublayerTransform":[1,0,0,0,0,1,0,0,0,0,1,0,0,0,0,1],"contentsRect":{"y":0,"x":0,"width":1,"height":1},"opacity":1,"edgeAntialiasingMask":251658240,"height":12,"hidden":false,"anchorPoint":{"pointX":0.5,"pointY":0.5}},"layers":[{"animations":[],"layers":[],"texturedRectangle":{"singleTextureOpacity":1,"textXHeight":0.47799999999999998,"textBaseline":0.8158543675357256,"isBackgroundTexture":true,"isVerticalText":false,"textColor":[0.53252053260803223,0.53252053260803223,0.53252053260803223,1],"textureType":6},"initialState":{"affineTransform":[1,0,0,1,0,0],"masksToBounds":false,"rotation":0,"scale":1,"position":{"pointX":11.044000267982483,"pointY":10.293756283266362},"width":17,"sublayerTransform":[1,0,0,0,0,1,0,0,0,0,1,0,0,0,0,1],"contentsRect":{"y":0,"x":0,"width":1,"height":1},"opacity":1,"edgeAntialiasingMask":0,"height":12,"hidden":false,"anchorPoint":{"pointX":0.5,"pointY":0.5}},"texture":"F7A29D79CCDDC21925033B223E2700F5"}]}]}]}},{"effects":[{"beginTime":0,"baseLayer":{"animations":[],"initialState":{"affineTransform":[1,0,0,1,0,0],"masksToBounds":false,"rotation":0,"scale":1,"position":{"pointX":365.40677165985107,"pointY":204.87212610244751},"width":718,"sublayerTransform":[1,0,0,0,0,1,0,0,0,0,1,0,0,0,0,1],"contentsRect":{"y":0,"x":0,"width":1,"height":1},"opacity":1,"edgeAntialiasingMask":251658240,"height":397,"hidden":false,"anchorPoint":{"pointX":0.5,"pointY":0.5}},"objectID":"7C477E16-AD9D-4CC7-B052-550D6A50C152","layers":[{"animations":[],"initialState":{"affineTransform":[1,0,0,1,0,0],"masksToBounds":false,"rotation":0,"scale":1,"position":{"pointX":353.59322834014893,"pointY":196.12787389755249},"width":718,"sublayerTransform":[1,0,0,0,0,1,0,0,0,0,1,-0.00093354433244735948,0,0,0,1],"contentsRect":{"y":0,"x":0,"width":1,"height":1},"opacity":1,"edgeAntialiasingMask":251658240,"height":397,"hidden":false,"anchorPoint":{"pointX":0.49246967735396785,"pointY":0.49402487127846972}},"layers":[{"animations":[{"additive":false,"timeOffset":0,"beginTime":1e-100,"repeatCount":0,"fillMode":"both","duration":0.01,"autoreverses":false,"animations":[{"additive":false,"timeOffset":0,"beginTime":0,"from":{"scalar":true},"repeatCount":0,"fillMode":"both","duration":0.0001,"autoreverses":false,"property":"hidden","to":{"scalar":false},"removedOnCompletion":true},{"additive":false,"timeOffset":0,"beginTime":0.0001,"from":{"scalar":false},"repeatCount":0,"fillMode":"forwards","duration":0.0099000000000000008,"autoreverses":false,"property":"hidden","to":{"scalar":false},"removedOnCompletion":true}],"removedOnCompletion":false}],"layers":[],"texturedRectangle":{"isBackgroundTexture":true,"singleTextureOpacity":1,"textureType":5,"textBaseline":0,"textXHeight":0,"isVerticalText":false},"initialState":{"affineTransform":[1,0,0,1,0,0],"masksToBounds":false,"rotation":0,"scale":1,"position":{"pointX":356.59322834014893,"pointY":196.12787389755249},"width":718,"sublayerTransform":[1,0,0,0,0,1,0,0,0,0,1,0,0,0,0,1],"contentsRect":{"y":0,"x":0,"width":1,"height":1},"opacity":1,"edgeAntialiasingMask":0,"height":397,"hidden":true,"anchorPoint":{"pointX":0.5,"pointY":0.5}},"texture":"ACA29B21A7C35BBFE2D04B0DFB1F9D0F"}]}]},"effects":[],"duration":0.01,"type":"buildIn","attributes":{"direction":0},"name":"apple:appear","objectID":"7C477E16-AD9D-4CC7-B052-550D6A50C152"}],"automaticPlay":false,"hyperlinks":[],"accessibility":[{"text":"These seemingly tiny Web communities can really punch above their weight class when it comes to influencing the greater Web","targetRectangle":{"y":149.14644777151989,"x":128.42054882049561,"width":404.64999999999998,"height":123.37515258789062}},{"text":"Twitter top influencers for alternative URLs ","targetRectangle":{"y":88.807092189788818,"x":34.098265171051025,"width":316.31899999999996,"height":22.942489133474737}},{"text":"\/r\/The_Donald (2.72%)","targetRectangle":{"y":111.74958132326356,"x":90.347399592399597,"width":147.73500000000001,"height":20.030619838535131}},{"text":"\/pol\/ (1.96%)","targetRectangle":{"y":131.78020116179869,"x":90.347399592399597,"width":84.225000000000023,"height":20.030619838535131}},{"text":"\/r\/politics (1.1%)","targetRectangle":{"y":151.81082100033382,"x":90.347399592399597,"width":106.72500000000002,"height":20.030619838535131}},{"text":"Twitter top influencers for mainstream URLs","targetRectangle":{"y":200.78392997234369,"x":34.098265171051025,"width":320.58599999999996,"height":27.942489133474737}},{"text":"\/r\/politics (4.29%)","targetRectangle":{"y":228.72641910581842,"x":90.347399592399597,"width":115.065,"height":20.030619838535131}},{"text":"\/pol\/ (3.01%)","targetRectangle":{"y":248.75703894435355,"x":90.347399592399597,"width":84.225000000000023,"height":20.030619838535131}},{"text":"\/r\/The_Donald (2.97%)","targetRectangle":{"y":268.78765878288868,"x":90.347399592399597,"width":147.73500000000001,"height":17.625091552734375}},{"text":"Picture 3","targetRectangle":{"y":62.000316619873047,"x":299.61660766601562,"width":407.88473510742188,"height":290.769287109375}},{"text":"￼","targetRectangle":{"y":379.30624362136621,"x":667.05599963665009,"width":13.344000000000051,"height":13.7000732421875}},{"text":"How Communities Influence Each Other?","targetRectangle":{"y":11.819133758544922,"x":24.80990743637085,"width":618.05200000000002,"height":40.15020751953125}}],"baseLayer":{"animations":[],"initialState":{"affineTransform":[1,0,0,1,0,0],"masksToBounds":false,"rotation":0,"scale":1,"position":{"pointX":360,"pointY":202.5},"width":720,"sublayerTransform":[1,0,0,0,0,1,0,0,0,0,1,0,0,0,0,1],"contentsRect":{"y":0,"x":0,"width":1,"height":1},"opacity":1,"edgeAntialiasingMask":251658240,"height":405,"hidden":false,"anchorPoint":{"pointX":0.5,"pointY":0.5}},"layers":[{"animations":[],"initialState":{"affineTransform":[1,0,0,1,0,0],"masksToBounds":false,"rotation":0,"scale":1,"position":{"pointX":360,"pointY":202.5},"width":720,"sublayerTransform":[1,0,0,0,0,1,0,0,0,0,1,0,0,0,0,1],"contentsRect":{"y":0,"x":0,"width":1,"height":1},"opacity":1,"edgeAntialiasingMask":251658240,"height":405,"hidden":false,"anchorPoint":{"pointX":0.5,"pointY":0.5}},"layers":[{"animations":[],"initialState":{"affineTransform":[1,0,0,1,0,0],"masksToBounds":false,"rotation":0,"scale":1,"position":{"pointX":360,"pointY":202.5},"width":720,"sublayerTransform":[1,0,0,0,0,1,0,0,0,0,1,0,0,0,0,1],"contentsRect":{"y":0,"x":0,"width":1,"height":1},"opacity":1,"edgeAntialiasingMask":251658240,"height":405,"hidden":false,"anchorPoint":{"pointX":0.5,"pointY":0.5}},"layers":[{"animations":[],"layers":[],"texturedRectangle":{"isBackgroundTexture":true,"singleTextureOpacity":1,"textureType":1,"textBaseline":0,"textXHeight":0,"isVerticalText":false},"initialState":{"affineTransform":[1,0,0,1,0,0],"masksToBounds":false,"rotation":0,"scale":1,"position":{"pointX":360,"pointY":202.5},"width":720,"sublayerTransform":[1,0,0,0,0,1,0,0,0,0,1,0,0,0,0,1],"contentsRect":{"y":0,"x":0,"width":1,"height":1},"opacity":1,"edgeAntialiasingMask":0,"height":405,"hidden":false,"anchorPoint":{"pointX":0.5,"pointY":0.5}},"texture":"1BFD4A8A3262821D77512FEA63730126"}]}]},{"animations":[],"initialState":{"affineTransform":[1,0,0,1,0,0],"masksToBounds":false,"rotation":0,"scale":1,"position":{"pointX":360,"pointY":202.5},"width":720,"sublayerTransform":[1,0,0,0,0,1,0,0,0,0,1,0,0,0,0,1],"contentsRect":{"y":0,"x":0,"width":1,"height":1},"opacity":1,"edgeAntialiasingMask":251658240,"height":405,"hidden":false,"anchorPoint":{"pointX":0.5,"pointY":0.5}},"layers":[{"animations":[],"initialState":{"affineTransform":[1,0,0,1,0,0],"masksToBounds":false,"rotation":0,"scale":1,"position":{"pointX":505.11660766601562,"pointY":208.50031661987305},"width":411,"sublayerTransform":[1,0,0,0,0,1,0,0,0,0,1,0,0,0,0,1],"contentsRect":{"y":0,"x":0,"width":1,"height":1},"opacity":1,"edgeAntialiasingMask":251658240,"height":293,"hidden":false,"anchorPoint":{"pointX":0.5,"pointY":0.5}},"objectID":"B8E87B26-F9FB-4880-8E13-91E059967AC1","layers":[{"animations":[],"layers":[],"texturedRectangle":{"isBackgroundTexture":true,"singleTextureOpacity":1,"textureType":5,"textBaseline":0,"textXHeight":0,"isVerticalText":false},"initialState":{"affineTransform":[1,0,0,1,0,0],"masksToBounds":false,"rotation":0,"scale":1,"position":{"pointX":203.88339233398438,"pointY":145.49968338012695},"width":411,"sublayerTransform":[1,0,0,0,0,1,0,0,0,0,1,0,0,0,0,1],"contentsRect":{"y":0,"x":0,"width":1,"height":1},"opacity":1,"edgeAntialiasingMask":0,"height":293,"hidden":false,"anchorPoint":{"pointX":0.5,"pointY":0.5}},"texture":"0DF7A63E368CD5F4EF722AAF54AE841C"}]}]},{"animations":[],"initialState":{"affineTransform":[1,0,0,1,0,0],"masksToBounds":false,"rotation":0,"scale":1,"position":{"pointX":360,"pointY":202.5},"width":720,"sublayerTransform":[1,0,0,0,0,1,0,0,0,0,1,0,0,0,0,1],"contentsRect":{"y":0,"x":0,"width":1,"height":1},"opacity":1,"edgeAntialiasingMask":251658240,"height":405,"hidden":false,"anchorPoint":{"pointX":0.5,"pointY":0.5}},"layers":[{"animations":[],"initialState":{"affineTransform":[1,0,0,1,0,0],"masksToBounds":false,"rotation":0,"scale":1,"position":{"pointX":329.70990753173828,"pointY":17.719133853912354},"width":617,"sublayerTransform":[1,0,0,0,0,1,0,0,0,0,1,0,0,0,0,1],"contentsRect":{"y":0,"x":0,"width":1,"height":1},"opacity":1,"edgeAntialiasingMask":251658240,"height":31,"hidden":false,"anchorPoint":{"pointX":0.5,"pointY":0.5}},"layers":[{"animations":[],"layers":[],"texturedRectangle":{"singleTextureOpacity":1,"textXHeight":0.53193548387096778,"textBaseline":0.89861802131898938,"isBackgroundTexture":true,"isVerticalText":false,"textColor":[0.58435440063476562,0.21667070686817169,0.20682203769683838,1],"textureType":6},"initialState":{"affineTransform":[1,0,0,1,0,0],"masksToBounds":false,"rotation":0,"scale":1,"position":{"pointX":313.29009246826172,"pointY":28.280866146087646},"width":617,"sublayerTransform":[1,0,0,0,0,1,0,0,0,0,1,0,0,0,0,1],"contentsRect":{"y":0,"x":0,"width":1,"height":1},"opacity":1,"edgeAntialiasingMask":0,"height":31,"hidden":false,"anchorPoint":{"pointX":0.5,"pointY":0.5}},"texture":"C2B660CBAE4E04024987B6A2AAA101E6"}]}]},{"animations":[],"initialState":{"affineTransform":[1,0,0,1,0,0],"masksToBounds":false,"rotation":0,"scale":1,"position":{"pointX":360,"pointY":202.5},"width":720,"sublayerTransform":[1,0,0,0,0,1,0,0,0,0,1,0,0,0,0,1],"contentsRect":{"y":0,"x":0,"width":1,"height":1},"opacity":1,"edgeAntialiasingMask":251658240,"height":405,"hidden":false,"anchorPoint":{"pointX":0.5,"pointY":0.5}},"layers":[{"animations":[],"initialState":{"affineTransform":[1,0,0,1,0,0],"masksToBounds":false,"rotation":0,"scale":1,"position":{"pointX":174.49865818023682,"pointY":183.70709228515625},"width":324,"sublayerTransform":[1,0,0,0,0,1,0,0,0,0,1,0,0,0,0,1],"contentsRect":{"y":0,"x":0,"width":1,"height":1},"opacity":1,"edgeAntialiasingMask":251658240,"height":197,"hidden":false,"anchorPoint":{"pointX":0.5,"pointY":0.5}},"layers":[{"animations":[],"layers":[],"texturedRectangle":{"singleTextureOpacity":1,"textXHeight":0.041248730964467011,"textBaseline":1.0630623837956952,"isBackgroundTexture":true,"isVerticalText":false,"textColor":[0,0,0,1],"textureType":6},"initialState":{"affineTransform":[1,0,0,1,0,0],"masksToBounds":false,"rotation":0,"scale":1,"position":{"pointX":181.50134181976318,"pointY":103.29290771484375},"width":324,"sublayerTransform":[1,0,0,0,0,1,0,0,0,0,1,0,0,0,0,1],"contentsRect":{"y":0,"x":0,"width":1,"height":1},"opacity":1,"edgeAntialiasingMask":0,"height":197,"hidden":false,"anchorPoint":{"pointX":0.5,"pointY":0.5}},"texture":"DA4973FF21027C87B166D858FEECF4FC"}]}]},{"animations":[],"initialState":{"affineTransform":[1,0,0,1,0,0],"masksToBounds":false,"rotation":0,"scale":1,"position":{"pointX":360,"pointY":202.5},"width":720,"sublayerTransform":[1,0,0,0,0,1,0,0,0,0,1,0,0,0,0,1],"contentsRect":{"y":0,"x":0,"width":1,"height":1},"opacity":1,"edgeAntialiasingMask":251658240,"height":405,"hidden":false,"anchorPoint":{"pointX":0.5,"pointY":0.5}},"layers":[{"animations":[],"initialState":{"affineTransform":[1,0,0,1,0,0],"masksToBounds":false,"rotation":0,"scale":1,"position":{"pointX":365.40677165985107,"pointY":204.87212610244751},"width":718,"sublayerTransform":[1,0,0,0,0,1,0,0,0,0,1,0,0,0,0,1],"contentsRect":{"y":0,"x":0,"width":1,"height":1},"opacity":1,"edgeAntialiasingMask":251658240,"height":397,"hidden":false,"anchorPoint":{"pointX":0.5,"pointY":0.5}},"objectID":"7C477E16-AD9D-4CC7-B052-550D6A50C152","layers":[{"animations":[],"layers":[],"texturedRectangle":{"isBackgroundTexture":true,"singleTextureOpacity":1,"textureType":5,"textBaseline":0,"textXHeight":0,"isVerticalText":false},"initialState":{"affineTransform":[1,0,0,1,0,0],"masksToBounds":false,"rotation":0,"scale":1,"position":{"pointX":356.59322834014893,"pointY":196.12787389755249},"width":718,"sublayerTransform":[1,0,0,0,0,1,0,0,0,0,1,0,0,0,0,1],"contentsRect":{"y":0,"x":0,"width":1,"height":1},"opacity":1,"edgeAntialiasingMask":0,"height":397,"hidden":true,"anchorPoint":{"pointX":0.5,"pointY":0.5}},"texture":"ACA29B21A7C35BBFE2D04B0DFB1F9D0F"}]}]},{"animations":[],"initialState":{"affineTransform":[1,0,0,1,0,0],"masksToBounds":false,"rotation":0,"scale":1,"position":{"pointX":360,"pointY":202.5},"width":720,"sublayerTransform":[1,0,0,0,0,1,0,0,0,0,1,0,0,0,0,1],"contentsRect":{"y":0,"x":0,"width":1,"height":1},"opacity":1,"edgeAntialiasingMask":251658240,"height":405,"hidden":false,"anchorPoint":{"pointX":0.5,"pointY":0.5}},"layers":[{"animations":[],"initialState":{"affineTransform":[1,0,0,1,0,0],"masksToBounds":false,"rotation":0,"scale":1,"position":{"pointX":670.95599973201752,"pointY":381.70624371673364},"width":17,"sublayerTransform":[1,0,0,0,0,1,0,0,0,0,1,0,0,0,0,1],"contentsRect":{"y":0,"x":0,"width":1,"height":1},"opacity":1,"edgeAntialiasingMask":251658240,"height":12,"hidden":false,"anchorPoint":{"pointX":0.5,"pointY":0.5}},"layers":[{"animations":[],"layers":[],"texturedRectangle":{"singleTextureOpacity":1,"textXHeight":0.47799999999999998,"textBaseline":0.8158543675357256,"isBackgroundTexture":true,"isVerticalText":false,"textColor":[0.53252053260803223,0.53252053260803223,0.53252053260803223,1],"textureType":6},"initialState":{"affineTransform":[1,0,0,1,0,0],"masksToBounds":false,"rotation":0,"scale":1,"position":{"pointX":11.044000267982483,"pointY":10.293756283266362},"width":17,"sublayerTransform":[1,0,0,0,0,1,0,0,0,0,1,0,0,0,0,1],"contentsRect":{"y":0,"x":0,"width":1,"height":1},"opacity":1,"edgeAntialiasingMask":0,"height":12,"hidden":false,"anchorPoint":{"pointX":0.5,"pointY":0.5}},"texture":"F7A29D79CCDDC21925033B223E2700F5"}]}]}]}},{"effects":[{"beginTime":0,"baseLayer":{"animations":[],"initialState":{"affineTransform":[1,0,0,1,0,0],"masksToBounds":false,"rotation":0,"scale":1,"position":{"pointX":360,"pointY":202.5},"width":720,"sublayerTransform":[1,0,0,0,0,1,0,0,0,0,1,0,0,0,0,1],"contentsRect":{"y":0,"x":0,"width":1,"height":1},"opacity":1,"edgeAntialiasingMask":251658240,"height":405,"hidden":false,"anchorPoint":{"pointX":0.5,"pointY":0.5}},"objectID":"0","layers":[{"animations":[],"initialState":{"affineTransform":[1,0,0,1,0,0],"masksToBounds":false,"rotation":0,"scale":1,"position":{"pointX":360,"pointY":202.5},"width":720,"sublayerTransform":[1,0,0,0,0,1,0,0,0,0,1,-0.00093354433244735948,0,0,0,1],"contentsRect":{"y":0,"x":0,"width":1,"height":1},"opacity":1,"edgeAntialiasingMask":251658240,"height":405,"hidden":false,"anchorPoint":{"pointX":0.5,"pointY":0.5}},"layers":[{"animations":[],"layers":[],"texturedRectangle":{"isBackgroundTexture":false,"singleTextureOpacity":1,"textureType":0,"textBaseline":0,"textXHeight":0,"isVerticalText":false},"initialState":{"affineTransform":[1,0,0,1,0,0],"masksToBounds":false,"rotation":0,"scale":1,"position":{"pointX":360,"pointY":202.5},"width":720,"sublayerTransform":[1,0,0,0,0,1,0,0,0,0,1,0,0,0,0,1],"contentsRect":{"y":0,"x":0,"width":1,"height":1},"opacity":1,"edgeAntialiasingMask":0,"height":405,"hidden":false,"anchorPoint":{"pointX":0.5,"pointY":0.5}},"texture":"414597C22F1B90C06D244B46B4458540"},{"animations":[{"additive":false,"timeOffset":0,"beginTime":0,"from":{"scalar":false},"repeatCount":0,"fillMode":"both","duration":0.01,"autoreverses":false,"property":"hidden","to":{"scalar":true},"removedOnCompletion":false}],"layers":[],"texturedRectangle":{"isBackgroundTexture":false,"singleTextureOpacity":1,"textureType":0,"textBaseline":0,"textXHeight":0,"isVerticalText":false},"initialState":{"affineTransform":[1,0,0,1,0,0],"masksToBounds":false,"rotation":0,"scale":1,"position":{"pointX":360,"pointY":202.5},"width":720,"sublayerTransform":[1,0,0,0,0,1,0,0,0,0,1,0,0,0,0,1],"contentsRect":{"y":0,"x":0,"width":1,"height":1},"opacity":1,"edgeAntialiasingMask":0,"height":405,"hidden":false,"anchorPoint":{"pointX":0.5,"pointY":0.5}},"texture":"500251E8DEC407F09E1DCC95A9A04274"}]}]},"effects":[],"duration":0.01,"type":"transition","attributes":{"direction":0},"name":"none","objectID":"0"}],"automaticPlay":false,"hyperlinks":[],"accessibility":[{"text":"These seemingly tiny Web communities can really punch above their weight class when it comes to influencing the greater Web","targetRectangle":{"y":149.14644777151989,"x":128.42054882049561,"width":404.64999999999998,"height":123.37515258789062}},{"text":"Twitter top influencers for alternative URLs ","targetRectangle":{"y":88.807092189788818,"x":34.098265171051025,"width":316.31899999999996,"height":22.942489133474737}},{"text":"\/r\/The_Donald (2.72%)","targetRectangle":{"y":111.74958132326356,"x":90.347399592399597,"width":147.73500000000001,"height":20.030619838535131}},{"text":"\/pol\/ (1.96%)","targetRectangle":{"y":131.78020116179869,"x":90.347399592399597,"width":84.225000000000023,"height":20.030619838535131}},{"text":"\/r\/politics (1.1%)","targetRectangle":{"y":151.81082100033382,"x":90.347399592399597,"width":106.72500000000002,"height":20.030619838535131}},{"text":"Twitter top influencers for mainstream URLs","targetRectangle":{"y":200.78392997234369,"x":34.098265171051025,"width":320.58599999999996,"height":27.942489133474737}},{"text":"\/r\/politics (4.29%)","targetRectangle":{"y":228.72641910581842,"x":90.347399592399597,"width":115.065,"height":20.030619838535131}},{"text":"\/pol\/ (3.01%)","targetRectangle":{"y":248.75703894435355,"x":90.347399592399597,"width":84.225000000000023,"height":20.030619838535131}},{"text":"\/r\/The_Donald (2.97%)","targetRectangle":{"y":268.78765878288868,"x":90.347399592399597,"width":147.73500000000001,"height":17.625091552734375}},{"text":"Picture 3","targetRectangle":{"y":62.000316619873047,"x":299.61660766601562,"width":407.88473510742188,"height":290.769287109375}},{"text":"￼","targetRectangle":{"y":379.30624362136621,"x":667.05599963665009,"width":13.344000000000051,"height":13.7000732421875}},{"text":"How Communities Influence Each Other?","targetRectangle":{"y":11.819133758544922,"x":24.80990743637085,"width":618.05200000000002,"height":40.15020751953125}}],"baseLayer":{"animations":[],"initialState":{"affineTransform":[1,0,0,1,0,0],"masksToBounds":false,"rotation":0,"scale":1,"position":{"pointX":360,"pointY":202.5},"width":720,"sublayerTransform":[1,0,0,0,0,1,0,0,0,0,1,0,0,0,0,1],"contentsRect":{"y":0,"x":0,"width":1,"height":1},"opacity":1,"edgeAntialiasingMask":251658240,"height":405,"hidden":false,"anchorPoint":{"pointX":0.5,"pointY":0.5}},"objectID":"0","layers":[{"animations":[],"initialState":{"affineTransform":[1,0,0,1,0,0],"masksToBounds":false,"rotation":0,"scale":1,"position":{"pointX":360,"pointY":202.5},"width":720,"sublayerTransform":[1,0,0,0,0,1,0,0,0,0,1,-0.00093354433244735948,0,0,0,1],"contentsRect":{"y":0,"x":0,"width":1,"height":1},"opacity":1,"edgeAntialiasingMask":251658240,"height":405,"hidden":false,"anchorPoint":{"pointX":0.5,"pointY":0.5}},"layers":[{"animations":[],"layers":[],"texturedRectangle":{"isBackgroundTexture":false,"singleTextureOpacity":1,"textureType":0,"textBaseline":0,"textXHeight":0,"isVerticalText":false},"initialState":{"affineTransform":[1,0,0,1,0,0],"masksToBounds":false,"rotation":0,"scale":1,"position":{"pointX":360,"pointY":202.5},"width":720,"sublayerTransform":[1,0,0,0,0,1,0,0,0,0,1,0,0,0,0,1],"contentsRect":{"y":0,"x":0,"width":1,"height":1},"opacity":1,"edgeAntialiasingMask":0,"height":405,"hidden":false,"anchorPoint":{"pointX":0.5,"pointY":0.5}},"texture":"500251E8DEC407F09E1DCC95A9A04274"}]}]}}]}